pyprometheus/__init__.py
pyprometheus/compat.py
pyprometheus/const.py
pyprometheus/managers.py
pyprometheus/metrics.py
pyprometheus/registry.py
pyprometheus/storage.py
pyprometheus/values.py
pyprometheus/contrib/__init__.py
pyprometheus/contrib/graphite.py
pyprometheus/contrib/uwsgi_features.py
pyprometheus/scripts/__init__.py
pyprometheus/utils/#memory.py#
pyprometheus/utils/__init__.py
pyprometheus/utils/exposition.py
pyprometheus-0.0.9.dist-info/DESCRIPTION.rst
pyprometheus-0.0.9.dist-info/METADATA
pyprometheus-0.0.9.dist-info/RECORD
pyprometheus-0.0.9.dist-info/WHEEL
pyprometheus-0.0.9.dist-info/entry_points.txt
pyprometheus-0.0.9.dist-info/metadata.json
pyprometheus-0.0.9.dist-info/top_level.txt
