Metadata-Version: 2.0
Name: pyprometheus
Version: 0.0.9
Summary: Prometheus python client and instrumentation library
Home-page: https://github.com/Lispython/pyprometheus
Author: Alexandr Lispython
Author-email: lispython@users.noreply.github.com
License: BSD
Platform: UNKNOWN
Classifier: Intended Audience :: Developers
Classifier: Intended Audience :: System Administrators
Classifier: Operating System :: OS Independent
Classifier: Operating System :: POSIX
Classifier: Programming Language :: Python :: 2
Classifier: Programming Language :: Python :: 2.7
Classifier: Programming Language :: Python
Classifier: Programming Language :: Python :: Implementation :: CPython
Classifier: Topic :: Software Development
Classifier: Topic :: System :: Monitoring
Classifier: Topic :: Software Development :: Libraries
Classifier: Topic :: System :: Networking :: Monitoring
Provides-Extra: tests
Requires-Dist: flake8 (==3.2.1); extra == 'tests'
Requires-Dist: flake8-comprehensions (==1.2.1); extra == 'tests'
Requires-Dist: flake8-quotes (==0.9.0); extra == 'tests'
Requires-Dist: ipdb; extra == 'tests'
Requires-Dist: pytest (==3.0.6); extra == 'tests'
Requires-Dist: pytest-cov (==2.4.0); extra == 'tests'
Requires-Dist: pytest-flake8 (==0.8.1); extra == 'tests'
Requires-Dist: tox (==2.3.2); extra == 'tests'
Requires-Dist: uwsgi (==2.0.14); extra == 'tests'
